[
  {
    "id": "folio_calendar-8.0.100000549",
    "action": "enable"
  },
  {
    "id": "folio_checkin-7.2.100000407",
    "action": "enable"
  },
  {
    "id": "folio_checkout-8.2.100000414",
    "action": "enable"
  },
  {
    "id": "folio_circulation-7.2.100000929",
    "action": "enable"
  },
  {
    "id": "folio_developer-6.4.100000352",
    "action": "enable"
  },
  {
    "id": "folio_inventory-9.3.1000002332",
    "action": "enable"
  },
  {
    "id": "folio_myprofile-7.2.100000177",
    "action": "enable"
  },
  {
    "id": "folio_plugin-create-inventory-records-3.3.100000210",
    "action": "enable"
  },
  {
    "id": "folio_plugin-find-instance-6.4.100000240",
    "action": "enable"
  },
  {
    "id": "folio_plugin-find-user-6.4.100000162",
    "action": "enable"
  },
  {
    "id": "folio_requests-7.2.1000001219",
    "action": "enable"
  },
  {
    "id": "folio_servicepoints-6.3.100000112",
    "action": "enable"
  },
  {
    "id": "folio_stripes-core-8.3.100000738",
    "action": "enable"
  },
  {
    "id": "folio_stripes-smart-components-7.3.1000001141",
    "action": "enable"
  },
  {
    "id": "folio_tags-6.3.100000106",
    "action": "enable"
  },
  {
    "id": "folio_tenant-settings-7.3.100000393",
    "action": "enable"
  },
  {
    "id": "folio_users-8.3.1000002286",
    "action": "enable"
  }
]
